Metadata-Version: 2.1
Name: pokazowka
Version: 1.1.1
Summary: Pakiet testowy
Home-page: http://example.com
Author: gmalek
